{
  "id": "525ceab6-f149-42db-8ae9-8bf7742c6e31",
  "prevId": "36e1ae40-ecf8-4435-a586-547aeedb3c46",
  "version": "7",
  "dialect": "postgresql",
  "tables": {
    "public.clientes": {
      "name": "clientes",
      "schema": "",
      "columns": {
        "id": {
          "name": "id",
          "type": "integer",
          "primaryKey": true,
          "notNull": true,
          "identity": {
            "type": "always",
            "name": "clientes_id_seq",
            "schema": "public",
            "increment": "1",
            "startWith": "1",
            "minValue": "1",
            "maxValue": "2147483647",
            "cache": "1",
            "cycle": false
          }
        },
        "nome": {
          "name": "nome",
          "type": "text",
          "primaryKey": false,
          "notNull": true
        },
        "email": {
          "name": "email",
          "type": "text",
          "primaryKey": false,
          "notNull": true
        }
      },
      "indexes": {},
      "foreignKeys": {},
      "compositePrimaryKeys": {},
      "uniqueConstraints": {
        "clientes_email_unique": {
          "name": "clientes_email_unique",
          "nullsNotDistinct": false,
          "columns": [
            "email"
          ]
        }
      },
      "policies": {},
      "checkConstraints": {},
      "isRLSEnabled": false
    },
    "public.pedidos": {
      "name": "pedidos",
      "schema": "",
      "columns": {
        "id": {
          "name": "id",
          "type": "integer",
          "primaryKey": true,
          "notNull": true,
          "identity": {
            "type": "always",
            "name": "pedidos_id_seq",
            "schema": "public",
            "increment": "1",
            "startWith": "1",
            "minValue": "1",
            "maxValue": "2147483647",
            "cache": "1",
            "cycle": false
          }
        },
        "cliente_id": {
          "name": "cliente_id",
          "type": "integer",
          "primaryKey": false,
          "notNull": false
        },
        "valor": {
          "name": "valor",
          "type": "integer",
          "primaryKey": false,
          "notNull": true
        },
        "produto_id": {
          "name": "produto_id",
          "type": "integer",
          "primaryKey": false,
          "notNull": true
        }
      },
      "indexes": {},
      "foreignKeys": {
        "pedidos_cliente_id_clientes_id_fk": {
          "name": "pedidos_cliente_id_clientes_id_fk",
          "tableFrom": "pedidos",
          "tableTo": "clientes",
          "columnsFrom": [
            "cliente_id"
          ],
          "columnsTo": [
            "id"
          ],
          "onDelete": "no action",
          "onUpdate": "no action"
        },
        "pedidos_produto_id_produtos_id_fk": {
          "name": "pedidos_produto_id_produtos_id_fk",
          "tableFrom": "pedidos",
          "tableTo": "produtos",
          "columnsFrom": [
            "produto_id"
          ],
          "columnsTo": [
            "id"
          ],
          "onDelete": "no action",
          "onUpdate": "no action"
        }
      },
      "compositePrimaryKeys": {},
      "uniqueConstraints": {},
      "policies": {},
      "checkConstraints": {},
      "isRLSEnabled": false
    },
    "public.produtos": {
      "name": "produtos",
      "schema": "",
      "columns": {
        "id": {
          "name": "id",
          "type": "integer",
          "primaryKey": true,
          "notNull": true,
          "identity": {
            "type": "always",
            "name": "produtos_id_seq",
            "schema": "public",
            "increment": "1",
            "startWith": "1",
            "minValue": "1",
            "maxValue": "2147483647",
            "cache": "1",
            "cycle": false
          }
        },
        "nome": {
          "name": "nome",
          "type": "text",
          "primaryKey": false,
          "notNull": true
        },
        "preco": {
          "name": "preco",
          "type": "integer",
          "primaryKey": false,
          "notNull": true
        }
      },
      "indexes": {},
      "foreignKeys": {},
      "compositePrimaryKeys": {},
      "uniqueConstraints": {},
      "policies": {},
      "checkConstraints": {},
      "isRLSEnabled": false
    }
  },
  "enums": {},
  "schemas": {},
  "sequences": {},
  "roles": {},
  "policies": {},
  "views": {},
  "_meta": {
    "columns": {},
    "schemas": {},
    "tables": {}
  }
}